Workbook

Sheet 00_Übersicht
B1: Allianz Suisse — Customer Experience & Perception
B2: Voice-of-Customer & Perception-Gap-Analyse · Datenbasis: öffentliche Quellen · Stand 2026-06-16
B4: Management Summary
B5: Allianz Suisse wird in repräsentativen Befragungen als solide, aber durchgehend hinter Marktführer Mobiliar wahrgenommen (comparis 2025 Silber 5.1 vs. Gold 5.3; bonus.ch 2026 Hausrat letzter Platz 11/11; NPS +8 vs. +45, Stand 2017–19). In unaufgeforderten Kanälen (Trustpilot 1.5/5) ist das Bild deutlich negativer — selbstselektiv, aber aufschlussreich. Vier Pain Points tauchen in BEIDEN Ebenen auf und widersprechen direkt dem Markenversprechen: Schadenfall, Erreichbarkeit, Preis-Leistung, Digitalisierung.
B9: Kennzahlen auf einen Blick
B10: Trustpilot allianz.ch | D10: comparis 2025 | F10: bonus.ch 2026 Hausrat
B11: 1.5 / 5 | D11: Silber 5.1 | F11: Platz 11/11
B12: ~239 Reviews · unaufgefordert, verzerrt | D12: Auto & Hausrat · Mobiliar Gold 5.3 | F12: letzter; Weiterempfehlung 84% vs. 96%
B14: checkall Preis-Leistung | D14: NPS-Rückstand (2017–19) | F14: checkall Gesamt (Umfrage)
B15: 4.0 / 5 | D15: +8 vs. +45 | F15: 4.2 / 5
B16: schwächste Dimension | D16: ~37 Punkte hinter Mobiliar | F16: ‚gut‘ · >5'400 Teilnehmende
B18: Inhalt der Arbeitsmappe
B19: 01_VoC_Daten | C19: Kodierte Kundenfeedbacks (Thema, Phase, Sentiment, Frequenz, Impact)
B20: 02_Priorisierung | C20: Pain-Point-Priorisierung (Frequenz × Impact) + Quick-Win-Logik
B21: 03_Benchmark | C21: Wettbewerbsvergleich Zufriedenheit & NPS
B22: 04_Perception_Gap | C22: Markenversprechen vs. erlebte Realität
B23: 05_Massnahmen_Tracker | C23: Massnahmen + Wirkungsmessung (Baseline → Ziel → Ist)
B24: 06_Wirkungsmessung | C24: KPI-Framework (NPS / CSAT / CES) & Tracking-Logik
B25: 07_Quellen | C25: Quellenverzeichnis mit Konfidenz

Sheet 01_VoC_Daten
A1: Voice of Customer — kodierte Pain Points
A2: Frequenz & Impact auf Skala 1–5. ‚In beiden Ebenen‘ = erscheint sowohl in repräsentativen Befragungen als auch in Beschwerdekanälen (= belastbares Signal).
A4: ID | B4: Pain Point | C4: Journey-Phase | D4: Sentiment | E4: Frequenz | F4: Impact | G4: Aufwand | H4: Priorität (F×I) | I4: Beide Ebenen | J4: Verletztes Versprechen | K4: Beispielzitat | L4: Belege
A5: P1 | B5: Schadenfall: Verzögerung, fragwürdige Ablehnungen, verspätete Auszahlung | C5: Schadenfall | D5: negativ | E5: 5 | F5: 5 | G5: 4 | H5: =E5*F5 -> 25 | I5: Ja | J5: ‚Im Schadenfall für Sie da. 7 Tage. 24 Stunden.‘ / ‚Ihr Sicherheitsnetz‘ | K5: 2 Monate nach dem Unfall mit Vollkasko und 6 Wochen nach Unterschrift habe ich noch immer kein Geld für mein Totalschaden-Auto gesehen. | L5: Trustpilot, checkall.ch, bonus.ch
A6: P2 | B6: Erreichbarkeit & Reaktionszeit: Hotline, E-Mail, Rückrufe | C6: Laufender Service/Vertragsänderung | D6: negativ | E6: 5 | F6: 4 | G6: 3 | H6: =E6*F6 -> 20 | I6: Ja | J6: ‚zuverlässige Partnerin‘ / ‚Sicherheitsnetz‘ | K6: Endlose Telefonwarteschlange, immer wieder leere Versprechungen. | L6: Trustpilot, checkall.ch
A7: P3 | B7: Preis-Leistung & Prämienerhöhungen: als unverhältnismässig empfunden | C7: Prämien/Rechnung | D7: negativ | E7: 4 | F7: 4 | G7: 2 | H7: =E7*F7 -> 16 | I7: Ja | J7: ‚echte Mehrwerte für unsere Kundinnen und Kunden‘ | K7: Der Kundendienst erklärte, dass 10% Prämienerhöhung normal seien — bei einer Inflation von nur 2,1%. | L7: checkall.ch, bonus.ch, Trustpilot
A8: P4 | B8: Digitale Einfachheit: keine dedizierte CH-App, schwaches Self-Service-Portal | C8: Digital/App | D8: negativ | E8: 3 | F8: 4 | G8: 5 | H8: =E8*F8 -> 12 | I8: Ja | J8: ‚einfache Lösungen‘ / Konzern-Strategie ‚Simplicity wins‘ | K8: Digitalisierung bei der Allianz leider absolut ungenügend. | L8: App-Store-Recherche, Trustpilot
A9: P5 | B9: Beratung/Offerte: Überversprechen & Verkaufsdruck beim Abschluss | C9: Offerte/Beratung | D9: negativ | E9: 3 | F9: 3 | G9: 3 | H9: =E9*F9 -> 9 | I9: — | J9: ‚bedarfsgerechte, ehrliche Beratung‘ / Vertrauen | K9: Der Berater hat versprochen, dass gewisse Dinge gedeckt seien — reine Lügen, nur damit er den Vertrag abschliessen konnte. | L9: Trustpilot
A10: P6 | B10: Vertragsausstieg & Retention: Kündigungen ignoriert, Nachforderungen, Inkasso ohne Vorkontakt | C10: Verlängerung/Kündigung | D10: negativ | E10: 3 | F10: 3 | G10: 2 | H10: =E10*F10 -> 9 | I10: — | J10: ‚zuverlässige Partnerin‘ | K10: Ich versuche seit Wochen meinen Vertrag zu kündigen … werde aber geflissentlich ignoriert. | L10: Trustpilot, checkall.ch
A11: POS1 | B11: Positiver Gegenpol: kompetente persönliche Beratung & einzelne reibungslose Schadenfälle | C11: Offerte/Beratung | D11: positiv | E11: 2 | F11: 3 | G11: 1 | H11: =E11*F11 -> 6 | I11: Ja | J11: — | K11: Das Personal der Schadensabteilung ist sehr freundlich und hilfsbereit. | L11: checkall.ch, Trustpilot

Sheet 02_Priorisierung
A1: Pain-Point-Priorisierung
A2: Priorität = Frequenz × Impact (max. 25). Quick Win = hohe Priorität bei geringem Aufwand. Werte verlinkt aus ‚01_VoC_Daten‘.
A4: ID | B4: Pain Point | C4: Frequenz | D4: Impact | E4: Aufwand | F4: Priorität | G4: Rang | H4: Klassifikation | I4: Empf. Sequenz
A5: P1 | B5: Schadenfall: Verzögerung, fragwürdige Ablehnungen, verspätete Auszahlung | C5: ='01_VoC_Daten'!E5 -> 5 | D5: ='01_VoC_Daten'!F5 -> 5 | E5: ='01_VoC_Daten'!G5 -> 4 | F5: =C5*D5 -> 25 | G5: =RANK(F5,$F$5:$F$10) -> 1 | H5: =IF(AND(F5>=16,E5<=2),"Quick Win",IF(F5>=20,"Top-Priorität",IF(F5>=12,"Strategisch","Mittel"))) -> Top-Priorität | I5: =IF(E5<=2,"Sofort (0–6 M)",IF(F5>=20,"Bald (0–12 M)","Mittelfristig")) -> Bald (0–12 M)
A6: P2 | B6: Erreichbarkeit & Reaktionszeit: Hotline, E-Mail, Rückrufe | C6: ='01_VoC_Daten'!E6 -> 5 | D6: ='01_VoC_Daten'!F6 -> 4 | E6: ='01_VoC_Daten'!G6 -> 3 | F6: =C6*D6 -> 20 | G6: =RANK(F6,$F$5:$F$10) -> 2 | H6: =IF(AND(F6>=16,E6<=2),"Quick Win",IF(F6>=20,"Top-Priorität",IF(F6>=12,"Strategisch","Mittel"))) -> Top-Priorität | I6: =IF(E6<=2,"Sofort (0–6 M)",IF(F6>=20,"Bald (0–12 M)","Mittelfristig")) -> Bald (0–12 M)
A7: P3 | B7: Preis-Leistung & Prämienerhöhungen: als unverhältnismässig empfunden | C7: ='01_VoC_Daten'!E7 -> 4 | D7: ='01_VoC_Daten'!F7 -> 4 | E7: ='01_VoC_Daten'!G7 -> 2 | F7: =C7*D7 -> 16 | G7: =RANK(F7,$F$5:$F$10) -> 3 | H7: =IF(AND(F7>=16,E7<=2),"Quick Win",IF(F7>=20,"Top-Priorität",IF(F7>=12,"Strategisch","Mittel"))) -> Quick Win | I7: =IF(E7<=2,"Sofort (0–6 M)",IF(F7>=20,"Bald (0–12 M)","Mittelfristig")) -> Sofort (0–6 M)
A8: P4 | B8: Digitale Einfachheit: keine dedizierte CH-App, schwaches Self-Service-Portal | C8: ='01_VoC_Daten'!E8 -> 3 | D8: ='01_VoC_Daten'!F8 -> 4 | E8: ='01_VoC_Daten'!G8 -> 5 | F8: =C8*D8 -> 12 | G8: =RANK(F8,$F$5:$F$10) -> 4 | H8: =IF(AND(F8>=16,E8<=2),"Quick Win",IF(F8>=20,"Top-Priorität",IF(F8>=12,"Strategisch","Mittel"))) -> Strategisch | I8: =IF(E8<=2,"Sofort (0–6 M)",IF(F8>=20,"Bald (0–12 M)","Mittelfristig")) -> Mittelfristig
A9: P5 | B9: Beratung/Offerte: Überversprechen & Verkaufsdruck beim Abschluss | C9: ='01_VoC_Daten'!E9 -> 3 | D9: ='01_VoC_Daten'!F9 -> 3 | E9: ='01_VoC_Daten'!G9 -> 3 | F9: =C9*D9 -> 9 | G9: =RANK(F9,$F$5:$F$10) -> 5 | H9: =IF(AND(F9>=16,E9<=2),"Quick Win",IF(F9>=20,"Top-Priorität",IF(F9>=12,"Strategisch","Mittel"))) -> Mittel | I9: =IF(E9<=2,"Sofort (0–6 M)",IF(F9>=20,"Bald (0–12 M)","Mittelfristig")) -> Mittelfristig
A10: P6 | B10: Vertragsausstieg & Retention: Kündigungen ignoriert, Nachforderungen, Inkasso ohne Vorkontakt | C10: ='01_VoC_Daten'!E10 -> 3 | D10: ='01_VoC_Daten'!F10 -> 3 | E10: ='01_VoC_Daten'!G10 -> 2 | F10: =C10*D10 -> 9 | G10: =RANK(F10,$F$5:$F$10) -> 5 | H10: =IF(AND(F10>=16,E10<=2),"Quick Win",IF(F10>=20,"Top-Priorität",IF(F10>=12,"Strategisch","Mittel"))) -> Mittel | I10: =IF(E10<=2,"Sofort (0–6 M)",IF(F10>=20,"Bald (0–12 M)","Mittelfristig")) -> Sofort (0–6 M)
A13: Lesehilfe Priorisierungsmatrix
A14: Top-Priorität | B14: Hohe Frequenz UND hoher Impact — zuerst angehen.
A15: Quick Win | B15: Hohe Wirkung bei geringem Aufwand — schnelle Erfolge.
A16: Strategisch | B16: Hoher Impact, höherer Aufwand — als Programm planen.
A17: Mittel | B17: Beobachten und bündeln.

Sheet 03_Benchmark
A1: Wettbewerbs-Benchmark
A3: Autoversicherung — Zufriedenheit (comparis 2025, Skala 1–6) | D3: 1–6 · Gold ab 5.2
A4: Anbieter | B4: NOTE | C4: Abstand zu Mobiliar
A5: Mobiliar | B5: 5.3 | C5: 0
A6: Vaudoise | B6: 5.2 | C6: -0.1
A7: Smile | B7: 5.2 | C7: -0.1
A8: Zurich | B8: 5.1 | C8: -0.2
A9: Allianz | B9: 5.1 | C9: -0.2
A10: AXA | B10: 5.1 | C10: -0.2
A12: Hausrat/Haftpflicht — Zufriedenheit (bonus.ch 2026, Skala 1–6) | D12: 1–6 · Allianz = letzter Platz
A13: Anbieter | B13: NOTE | C13: Abstand zu Mobiliar
A14: Mobiliar | B14: 5.5 | C14: 0
A15: Vaudoise | B15: 5.4 | C15: -0.1
A16: Helvetia | B16: 5.3 | C16: -0.2
A17: AXA | B17: 5.2 | C17: -0.3
A18: Zurich | B18: 5.2 | C18: -0.3
A19: Generali | B19: 5.2 | C19: -0.3
A20: Smile | B20: 5.2 | C20: -0.3
A21: Allianz | B21: 5.1 | C21: -0.4
A23: Net Promoter Score (Bain / HZ Insurance, Stand 2017–19) | D23: -100 bis +100
A24: Anbieter | B24: NPS | C24: Abstand zu Mobiliar
A25: Mobiliar | B25: 45 | C25: 0
A26: Branchenschnitt | B26: 18 | C26: -27
A27: Allianz | B27: 8 | C27: -37
A29: Weiterempfehlungsrate (bonus.ch 2026, %) | D29: %
A30: Anbieter | B30: WERT | C30: Abstand zu Mobiliar
A31: Mobiliar | B31: 96 | C31: 0
A32: Allianz | B32: 84 | C32: -12

Sheet 04_Perception_Gap
A1: Perception Gap — Versprechen vs. Realität
A2: Wo das öffentlich kommunizierte Markenversprechen am stärksten von der erlebten Realität abweicht.
A4: Thema | B4: Markenversprechen | C4: Erlebte Realität | D4: Gap | E4: Beleg Realität
A5: Schadenfall / Moment of Truth | B5: ‚Im Schadenfall für Sie da. 7 Tage. 24 Stunden.‘ | C5: Häufigstes Beschwerdethema: verzögerte/abgelehnte Schäden, ausbleibende Auszahlung, fehlende Empathie. | D5: GROSS | E5: Trustpilot, checkall.ch
A6: Erreichbarkeit / Verlässlichkeit | B6: ‚Ihr Sicherheitsnetz‘, ‚zuverlässige Partnerin‘ | C6: Lange Warteschlangen, unbeantwortete Mails, nicht eingehaltene Rückrufversprechen. | D6: GROSS | E6: Trustpilot, checkall.ch
A7: Einfachheit / Digitalisierung | B7: ‚einfache Lösungen und echte Mehrwerte‘; Konzern: ‚Simplicity wins‘ | C7: Keine bewertete dedizierte CH-App auffindbar (Mobiliar hat eine); ‚per Post wie im Mittelalter‘. | D7: GROSS | E7: App-Store-Recherche, Trustpilot
A8: Preis-Leistung / Mehrwert | B8: ‚echte Mehrwerte für unsere Kundinnen und Kunden‘ | C8: Preis-Leistung ist die plattformübergreifend schwächste Dimension (checkall 4.0; bonus letzter Platz). | D8: MITTEL-GROSS | E8: checkall.ch, bonus.ch
A9: Kundenloyalität / NPS-Anspruch | B9: Ziel ‚NPS Loyalty Leader‘ (75 %+ bis 2027); ausgezeichnet als ‚Best Customer-Centric Culture‘ 2024 | C9: NPS +8 vs. Mobiliar +45 (~37 Punkte Rückstand, Stand 2017–2019); bonus.ch Weiterempfehlung 84% vs. 96%. | D9: GROSS | E9: Bain/HZ Insurance; bonus.ch 2026

Sheet 05_Massnahmen_Tracker
A1: Massnahmen-Tracker & Wirkungsmessung
A2: Gelbe Felder = intern zu befüllen (Baseline/Ziel/Ist + Owner). Zielerreichung wird automatisch berechnet. Status per Dropdown.
A4: ID | B4: Massnahme | C4: Pain Point | D4: Typ | E4: Leit-KPI | F4: Baseline | G4: Zielwert | H4: Ist (aktuell) | I4: Zielerreichung | J4: Status | K4: Owner | L4: Horizont
A5: M1 | B5: Schaden-Versprechen einlösen: proaktive Status-Kommunikation & Closed Loop | C5: P1 | D5: Strategisch (mit Quick-Win-Anteil Kommunikation) | E5: Schaden-CSAT · Schaden-NPS · Ø Bearbeitungsdauer · % Erstrückmeldung <48h | I5: =IFERROR((H5-F5)/(G5-F5),"—") -> — | J5: Offen | L5: 0–12 Monate
A6: M2 | B6: Erreichbarkeit spürbar verbessern (Callback, SLA, KI-Triage) | C6: P2 | D6: Quick Win | E6: CES Service · Ø Wartezeit Telefon · Erreichbarkeitsquote · E-Mail-Antwortzeit | I6: =IFERROR((H6-F6)/(G6-F6),"—") -> — | J6: Offen | L6: 0–6 Monate
A7: M3 | B7: Prämienanpassungen proaktiv & verständlich erklären (Value statt Preis) | C7: P3 | D7: Quick Win | E7: CSAT nach Prämienkommunikation · Dimension Preis-Leistung (checkall/bonus) · Churn nach Prämienanpassung | I7: =IFERROR((H7-F7)/(G7-F7),"—") -> — | J7: Offen | L7: 0–9 Monate
A8: M4 | B8: ‚Simplicity wins‘ lokal einlösen: dedizierte CH-App & Portal-Ausbau | C8: P4 | D8: Strategisch | E8: App-/Portal-Adoption · CES Digital · Self-Service-Quote · App-Store-Rating CH | I8: =IFERROR((H8-F8)/(G8-F8),"—") -> — | J8: Offen | L8: 6–18 Monate
A9: M5 | B9: Beratungsqualität & Transparenz: Mis-Selling reduzieren | C9: P5 | D9: Mittel | E9: CSAT Beratung/Onboarding · Beschwerdequote Beratung · Frühstorno-Quote | I9: =IFERROR((H9-F9)/(G9-F9),"—") -> — | J9: Offen | L9: 3–12 Monate
A12: Beispiel-Zeitreihe (illustrativ) — KPI-Verlauf für Wirkungsmessung
A13: Difference-in-Differences-Logik: Zielmetrik über Zeit, Treatment vs. Kontrollgruppe. Werte intern befüllen.
A14: Quartal | B14: Baseline | C14: Q1 | D14: Q2 | E14: Q3 | F14: Q4 | G14: Δ ggü. Baseline
A15: Schaden-CSAT (Treatment) | G15: =IFERROR(F15-B15,"—") -> 0
A16: Schaden-CSAT (Kontrolle) | G16: =IFERROR(F16-B16,"—") -> 0
A17: Netto-Effekt (DiD) | G17: =IFERROR((F15-B15)-(F16-B16),"—") -> 0

Sheet 06_Wirkungsmessung
A1: Wirkungsmessungs-Framework
A3: Dachmetrik | B3: NPS (relational, periodisch) — Anschluss an Konzernziel ‚Loyalty Leader‘
A5: Metrik | B5: Definition | C5: Einsatz in Journey-Phasen
A6: CSAT | B6: Zufriedenheit mit konkreter Interaktion (Top-2-Box, Skala 1–5) | C6: Beratung, Abschluss, Onboarding, Schadenfall
A7: CES | B7: Mühelosigkeit (‚leicht gemacht‘, Skala 1–7; Gut ≥5.5) | C7: Laufender Service, Vertragsänderung, Schadenmeldung, Digital/App
A9: Closed-Loop-Feedback
A10: Inner Loop | B10: 1:1-Rückkontakt bei negativem Feedback <48h (v.a. Schaden/Service) — Problem lösen, Churn verhindern.
A11: Outer Loop | B11: Aggregierte Mustererkennung → systemische Prozess-/Produktverbesserungen.
A13: Wirkungslogik (5 Schritte)
A14: 1. Baseline der Zielmetrik vor Massnahme erheben
A15: 2. Konkreten Zielwert + Zeithorizont definieren
A16: 3. Kontrollgruppe / Difference-in-Differences zur Effekt-Isolierung
A17: 4. Zeitreihe statt Punktmessung (Saisonalität)
A18: 5. Verknüpfung mit Geschäfts-KPIs: Retention/Churn, Schadenkosten, Cost-to-Serve
A20: Priorisierungsmethode: Pain-Point-Score = Frequenz × Impact (Heatmap), Effort separat für Quick-Win-/Strategisch-Sequenzierung (ergänzend RICE).

Sheet 07_Quellen
A1: Quellenverzeichnis & Konfidenz
A3: Quelle | B3: Metrik / Beitrag | C3: Wert | D3: Ebene | E3: Konfidenz | F3: URL
A4: Trustpilot (allianz.ch) | B4: TrustScore | C4: 1.5 / 5 | D4: unaufgefordert (verzerrt) | E4: hoch für 1.5 & 239; mittel für Verteilung (~86% 1-Stern, ~11% 5-Stern) | F4: https://www.trustpilot.com/review/allianz.ch
A5: comparis.ch Kundenzufriedenheit 2025 (Innofact, ~4'500 Befragte) | B5: Zufriedenheitsnote / Siegel | C5: Auto 5.1 (Silber), Hausrat/Haftpflicht 5.1 (Silber) | D5: repräsentativ | E5: hoch für Hausrat 5.1; mittel für Auto (als ‚leicht unter 5.2-Gruppe‘ belegt, exakter Auto-Wert abgeleitet) | F5: https://www.watson.ch/schweiz/auto/753195428-ranking-so-zufrieden-sind-schweizer-mit-ihren-versicherungen
A6: bonus.ch Zufriedenheitsumfrage 2026 | B6: Note Kundenzufriedenheit | C6: Auto 5.2 (Platz 5/11, = Branchenschnitt), Hausrat/Haftpflicht 5.1 (LETZTER, 11/11) | D6: repräsentativ | E6: hoch (Original-PDF); separat gegenzuprüfen vor finaler Nutzung | F6: https://www.bonus.ch/Pdf/2026/Hausratversicherung.pdf
A7: checkall.ch Branchenumfrage (>5'400 Teilnehmende) | B7: Gesamtnote Kundenzufriedenheit | C7: 4.2 (‚gut‘) | D7: repräsentativ | E7: hoch | F7: https://www.checkall.ch/de/versicherung/versicherungsunternehmen/allianz
A8: checkall.ch Dimensionsnoten Allianz | B8: Dimensionsnoten | C8: Information/Kommunikation/Transparenz 4.3 · Service 4.1 · Preis-Leistung 4.0 · Kontaktbequemlichkeit 4.3 | D8: repräsentativ | E8: hoch | F8: https://www.checkall.ch/de/versicherung/versicherungsunternehmen/allianz
A9: Schweizer Branchenmonitor 2025 (SIQT / qualitaetstest.ch) | B9: Kundenzufriedenheit (0–10) | C9: Allianz NICHT in Top 5 (keiner Kernsparte) | D9: repräsentativ | E9: hoch | F9: https://www.qualitaetstest.ch/awards/schweizer-branchenmonitor/schweizer-branchenmonitor-2025-geld-banken-versicherungen/
A10: Bain & Company / HZ Insurance — NPS Schweiz | B10: Net Promoter Score | C10: Allianz +8 · Mobiliar +45 · Branchenschnitt ~+18 | D10: repräsentativ | E10: hoch für Werte; Aktualität niedrig — als Stand 2017–2019 kennzeichnen | F10: https://www.hzinsurance.ch/insurance/kundenmanagement-net-promoter-score-die-assekuranz-holt-auf
A11: moneyland.ch / Ipsos Zufriedenheitsumfrage 2025 (~1'500 Befragte) | B11: Kundenzufriedenheit gesamt (0–10) | C11: Allianz nicht in publizierten Top-Rängen | D11: repräsentativ | E11: mittel (Seite blockt Direktabruf) | F11: https://www.moneyland.ch/en/swiss-insurance-customer-satisfaction-survey-2025
A13: Datenlücken & Caveats
A14: • Keine bewertete dedizierte Allianz-Suisse-Endkunden-App im CH-App-Store/Play auffindbar (historische ‚myAllianz‘ seit 2019 depubliziert) — eigenständiger Befund (Wettbewerber Mobiliar hat eine).
A15: • Reddit/comparis-Forum/X für den Crawler nicht zugänglich — ungefiltertes Social-Feedback unvollständig.
A16: • Interne NPS/CSAT/CES-Werte nicht öffentlich — öffentliche Befragungen dienen als Proxy/Hypothese, intern zu validieren.
A17: • Bain-NPS-Einzelwerte stammen aus 2017–2019; bonus.ch-2026- und moneyland-2025-Werte vor finaler Präsentationsnutzung separat gegenprüfen.
A19: Disclaimer: Eigenständiges Bewerbungsprojekt auf Basis öffentlich zugänglicher Daten. Kein offizielles Allianz-Dokument. Konstruktive Absicht.
